{
    "alpha-nvim": {
        "cargoLocks": null,
        "date": "2023-11-28",
        "extract": null,
        "name": "alpha-nvim",
        "passthru": null,
        "pinned": false,
        "src": {
            "deepClone": false,
            "fetchSubmodules": false,
            "leaveDotGit": false,
            "name": null,
            "owner": "goolord",
            "repo": "alpha-nvim",
            "rev": "29074eeb869a6cbac9ce1fbbd04f5f5940311b32",
            "sha256": "sha256-R0Sjkhzn1Rueptcxnu69UataPWAnZnbwqRXoEHIivo4=",
            "type": "github"
        },
        "version": "29074eeb869a6cbac9ce1fbbd04f5f5940311b32"
    },
    "catppuccin": {
        "cargoLocks": null,
        "date": "2023-12-31",
        "extract": null,
        "name": "catppuccin",
        "passthru": null,
        "pinned": false,
        "src": {
            "deepClone": false,
            "fetchSubmodules": false,
            "leaveDotGit": false,
            "name": null,
            "owner": "catppuccin",
            "repo": "nvim",
            "rev": "5e36ca599f4aa41bdd87fbf2c5aae4397ac55074",
            "sha256": "sha256-3fe+Tc1rl1FSFdMyRKfDv7+/piIpj5RgWYgKeN1jx6s=",
            "type": "github"
        },
        "version": "5e36ca599f4aa41bdd87fbf2c5aae4397ac55074"
    },
    "cmp-buffer": {
        "cargoLocks": null,
        "date": "2022-08-10",
        "extract": null,
        "name": "cmp-buffer",
        "passthru": null,
        "pinned": false,
        "src": {
            "deepClone": false,
            "fetchSubmodules": false,
            "leaveDotGit": false,
            "name": null,
            "owner": "hrsh7th",
            "repo": "cmp-buffer",
            "rev": "3022dbc9166796b644a841a02de8dd1cc1d311fa",
            "sha256": "sha256-dG4U7MtnXThoa/PD+qFtCt76MQ14V1wX8GMYcvxEnbM=",
            "type": "github"
        },
        "version": "3022dbc9166796b644a841a02de8dd1cc1d311fa"
    },
    "cmp-cmdline": {
        "cargoLocks": null,
        "date": "2023-06-09",
        "extract": null,
        "name": "cmp-cmdline",
        "passthru": null,
        "pinned": false,
        "src": {
            "deepClone": false,
            "fetchSubmodules": false,
            "leaveDotGit": false,
            "name": null,
            "owner": "hrsh7th",
            "repo": "cmp-cmdline",
            "rev": "8ee981b4a91f536f52add291594e89fb6645e451",
            "sha256": "sha256-W8v/XhPjbvKSwCrfOAPihO2N9PEVnH5Cp/Fa25lNRw4=",
            "type": "github"
        },
        "version": "8ee981b4a91f536f52add291594e89fb6645e451"
    },
    "cmp-git": {
        "cargoLocks": null,
        "date": "2023-12-29",
        "extract": null,
        "name": "cmp-git",
        "passthru": null,
        "pinned": false,
        "src": {
            "deepClone": false,
            "fetchSubmodules": false,
            "leaveDotGit": false,
            "name": null,
            "owner": "petertriho",
            "repo": "cmp-git",
            "rev": "8d8993680d627c8f13bd85094eba84604107dbdd",
            "sha256": "sha256-HJvZXWUWff2+JBD4PRK55sgH8kOJmCCaeFNSlknA8tw=",
            "type": "github"
        },
        "version": "8d8993680d627c8f13bd85094eba84604107dbdd"
    },
    "cmp-nvim-lsp": {
        "cargoLocks": null,
        "date": "2023-12-10",
        "extract": null,
        "name": "cmp-nvim-lsp",
        "passthru": null,
        "pinned": false,
        "src": {
            "deepClone": false,
            "fetchSubmodules": false,
            "leaveDotGit": false,
            "name": null,
            "owner": "hrsh7th",
            "repo": "cmp-nvim-lsp",
            "rev": "5af77f54de1b16c34b23cba810150689a3a90312",
            "sha256": "sha256-/0sh9vJBD9pUuD7q3tNSQ1YLvxFMNykdg5eG+LjZAA8=",
            "type": "github"
        },
        "version": "5af77f54de1b16c34b23cba810150689a3a90312"
    },
    "cmp-path": {
        "cargoLocks": null,
        "date": "2022-10-03",
        "extract": null,
        "name": "cmp-path",
        "passthru": null,
        "pinned": false,
        "src": {
            "deepClone": false,
            "fetchSubmodules": false,
            "leaveDotGit": false,
            "name": null,
            "owner": "hrsh7th",
            "repo": "cmp-path",
            "rev": "91ff86cd9c29299a64f968ebb45846c485725f23",
            "sha256": "sha256-thppiiV3wjIaZnAXmsh7j3DUc6ceSCvGzviwFUnoPaI=",
            "type": "github"
        },
        "version": "91ff86cd9c29299a64f968ebb45846c485725f23"
    },
    "cmp_luasnip": {
        "cargoLocks": null,
        "date": "2023-10-09",
        "extract": null,
        "name": "cmp_luasnip",
        "passthru": null,
        "pinned": false,
        "src": {
            "deepClone": false,
            "fetchSubmodules": false,
            "leaveDotGit": false,
            "name": null,
            "owner": "saadparwaiz1",
            "repo": "cmp_luasnip",
            "rev": "05a9ab28b53f71d1aece421ef32fee2cb857a843",
            "sha256": "sha256-nUJJl2zyK/oSwz5RzI9j3gf9zpDfCImCYbPbVsyXgz8=",
            "type": "github"
        },
        "version": "05a9ab28b53f71d1aece421ef32fee2cb857a843"
    },
    "comment": {
        "cargoLocks": null,
        "date": "2023-08-07",
        "extract": null,
        "name": "comment",
        "passthru": null,
        "pinned": false,
        "src": {
            "deepClone": false,
            "fetchSubmodules": false,
            "leaveDotGit": false,
            "name": null,
            "owner": "numtostr",
            "repo": "comment.nvim",
            "rev": "0236521ea582747b58869cb72f70ccfa967d2e89",
            "sha256": "sha256-+dF1ZombrlO6nQggufSb0igXW5zwU++o0W/5ZA07cdc=",
            "type": "github"
        },
        "version": "0236521ea582747b58869cb72f70ccfa967d2e89"
    },
    "copilot-cmp": {
        "cargoLocks": null,
        "date": "2023-09-09",
        "extract": null,
        "name": "copilot-cmp",
        "passthru": null,
        "pinned": false,
        "src": {
            "deepClone": false,
            "fetchSubmodules": false,
            "leaveDotGit": false,
            "name": null,
            "owner": "zbirenbaum",
            "repo": "copilot-cmp",
            "rev": "72fbaa03695779f8349be3ac54fa8bd77eed3ee3",
            "sha256": "sha256-srgNohm/aJpswNJ5+T7p+zi9Jinp9e5FA8/wdk6VRiY=",
            "type": "github"
        },
        "version": "72fbaa03695779f8349be3ac54fa8bd77eed3ee3"
    },
    "copilot-lua": {
        "cargoLocks": null,
        "date": "2024-01-07",
        "extract": null,
        "name": "copilot-lua",
        "passthru": null,
        "pinned": false,
        "src": {
            "deepClone": false,
            "fetchSubmodules": false,
            "leaveDotGit": false,
            "name": null,
            "owner": "zbirenbaum",
            "repo": "copilot.lua",
            "rev": "b03617a6dc4bc88b65ab5deac1631da9a9c2dcaf",
            "sha256": "sha256-8/EPnigWaY2P4ZlVyu42DOQVOjRPgSCtmdOVbl2ACN8=",
            "type": "github"
        },
        "version": "b03617a6dc4bc88b65ab5deac1631da9a9c2dcaf"
    },
    "crates": {
        "cargoLocks": null,
        "date": "2024-01-03",
        "extract": null,
        "name": "crates",
        "passthru": null,
        "pinned": false,
        "src": {
            "deepClone": false,
            "fetchSubmodules": false,
            "leaveDotGit": false,
            "name": null,
            "owner": "saecki",
            "repo": "crates.nvim",
            "rev": "6d779c7b85139d89d92a4a0bcf0afbdcf0cd961a",
            "sha256": "sha256-v8Ow/5VdAJyWGMGmr4/8uz20a9z1QIpH6z01VdTiIcw=",
            "type": "github"
        },
        "version": "6d779c7b85139d89d92a4a0bcf0afbdcf0cd961a"
    },
    "editorconfig": {
        "cargoLocks": null,
        "date": "2023-01-10",
        "extract": null,
        "name": "editorconfig",
        "passthru": null,
        "pinned": false,
        "src": {
            "deepClone": false,
            "fetchSubmodules": false,
            "leaveDotGit": false,
            "name": null,
            "owner": "gpanders",
            "repo": "editorconfig.nvim",
            "rev": "5b9e303e1d6f7abfe616ce4cc8d3fffc554790bf",
            "sha256": "sha256-pR57tITdVGF4luEmmRYv/XFb35E3KDfcgYRijkPAc+Y=",
            "type": "github"
        },
        "version": "5b9e303e1d6f7abfe616ce4cc8d3fffc554790bf"
    },
    "fidget": {
        "cargoLocks": null,
        "date": "2023-11-09",
        "extract": null,
        "name": "fidget",
        "passthru": null,
        "pinned": false,
        "src": {
            "deepClone": false,
            "fetchSubmodules": false,
            "leaveDotGit": false,
            "name": null,
            "owner": "j-hui",
            "repo": "fidget.nvim",
            "rev": "2f7c08f45639a64a5c0abcf67321d52c3f499ae6",
            "sha256": "sha256-8Gl2Ck4YJGReSEq1Xeh1dpdRq4eImmrxvIHrfxdem3Q=",
            "type": "github"
        },
        "version": "2f7c08f45639a64a5c0abcf67321d52c3f499ae6"
    },
    "go-nvim": {
        "cargoLocks": null,
        "date": "2023-12-27",
        "extract": null,
        "name": "go-nvim",
        "passthru": null,
        "pinned": false,
        "src": {
            "deepClone": false,
            "fetchSubmodules": false,
            "leaveDotGit": false,
            "name": null,
            "owner": "ray-x",
            "repo": "go.nvim",
            "rev": "24d2fa373d55d9900cd4b502a88214dc17e6fab6",
            "sha256": "sha256-5ZQRFsVf7PUSDcamiZ4m/W/kHYG4Zm8KOMpYu7bDbjs=",
            "type": "github"
        },
        "version": "24d2fa373d55d9900cd4b502a88214dc17e6fab6"
    },
    "guihua-lua": {
        "cargoLocks": null,
        "date": "2023-12-06",
        "extract": null,
        "name": "guihua-lua",
        "passthru": null,
        "pinned": false,
        "src": {
            "deepClone": false,
            "fetchSubmodules": false,
            "leaveDotGit": false,
            "name": null,
            "owner": "ray-x",
            "repo": "guihua.lua",
            "rev": "9fb6795474918b492d9ab01b1ebaf85e8bf6fe0b",
            "sha256": "sha256-0fpcYEdWfpy8MatH8cjalGOQ7/tau6ciiuSV1t09BlY=",
            "type": "github"
        },
        "version": "9fb6795474918b492d9ab01b1ebaf85e8bf6fe0b"
    },
    "harpoon": {
        "cargoLocks": null,
        "date": "2024-01-06",
        "extract": null,
        "name": "harpoon",
        "passthru": null,
        "pinned": false,
        "src": {
            "deepClone": false,
            "fetchSubmodules": false,
            "leaveDotGit": false,
            "name": null,
            "owner": "ThePrimeagen",
            "repo": "harpoon",
            "rev": "2cd4e03372f7ee5692c8caa220f479ea07970f17",
            "sha256": "sha256-MUIGRoaFcCqqFatfnFJpnEOUmSYJgV2+teU/NXj6kgY=",
            "type": "github"
        },
        "version": "2cd4e03372f7ee5692c8caa220f479ea07970f17"
    },
    "indent-blankline": {
        "cargoLocks": null,
        "date": "2024-01-02",
        "extract": null,
        "name": "indent-blankline",
        "passthru": null,
        "pinned": false,
        "src": {
            "deepClone": false,
            "fetchSubmodules": false,
            "leaveDotGit": false,
            "name": null,
            "owner": "lukas-reineke",
            "repo": "indent-blankline.nvim",
            "rev": "3c8a185da4b8ab7aef487219f5e001b11d4b6aaf",
            "sha256": "sha256-azBQqGS3fw+zW8PTPRsdMzhfUnWg4XghKOKMHQgh9i8=",
            "type": "github"
        },
        "version": "3c8a185da4b8ab7aef487219f5e001b11d4b6aaf"
    },
    "lazy": {
        "cargoLocks": null,
        "date": "2023-11-04",
        "extract": null,
        "name": "lazy",
        "passthru": null,
        "pinned": false,
        "src": {
            "deepClone": false,
            "fetchSubmodules": false,
            "leaveDotGit": false,
            "name": null,
            "owner": "folke",
            "repo": "lazy.nvim",
            "rev": "96584866b9c5e998cbae300594d0ccfd0c464627",
            "sha256": "sha256-adBcg8iSSO5eRLuZJnmU6m7IiRJXjoMDzN6yH2JrQIc=",
            "type": "github"
        },
        "version": "96584866b9c5e998cbae300594d0ccfd0c464627"
    },
    "lazygit": {
        "cargoLocks": null,
        "date": "2023-12-15",
        "extract": null,
        "name": "lazygit",
        "passthru": null,
        "pinned": false,
        "src": {
            "deepClone": false,
            "fetchSubmodules": false,
            "leaveDotGit": false,
            "name": null,
            "owner": "kdheepak",
            "repo": "lazygit.nvim",
            "rev": "1e08e3f5ac1152339690140e61a4a32b3bdc7de5",
            "sha256": "sha256-fYNsHQeG/C6pAy2rHPN5h/bYJRc8IGQ8REKiU9TWQ+c=",
            "type": "github"
        },
        "version": "1e08e3f5ac1152339690140e61a4a32b3bdc7de5"
    },
    "lsp-status": {
        "cargoLocks": null,
        "date": "2022-08-03",
        "extract": null,
        "name": "lsp-status",
        "passthru": null,
        "pinned": false,
        "src": {
            "deepClone": false,
            "fetchSubmodules": false,
            "leaveDotGit": false,
            "name": null,
            "owner": "nvim-lua",
            "repo": "lsp-status.nvim",
            "rev": "54f48eb5017632d81d0fd40112065f1d062d0629",
            "sha256": "sha256-gmLeVnDyL8Zf5ZG92tP3mb/LAt438BxFtAi/Xax2zLI=",
            "type": "github"
        },
        "version": "54f48eb5017632d81d0fd40112065f1d062d0629"
    },
    "lspkind": {
        "cargoLocks": null,
        "date": "2023-12-25",
        "extract": null,
        "name": "lspkind",
        "passthru": null,
        "pinned": false,
        "src": {
            "deepClone": false,
            "fetchSubmodules": false,
            "leaveDotGit": false,
            "name": null,
            "owner": "onsails",
            "repo": "lspkind.nvim",
            "rev": "7f26cf5e27e2bd910ce0ea00c514da2bf97423b8",
            "sha256": "sha256-PcSHrPgPvElT6UJa+cT7L6iAzhE0tvn59bsDjq6nz8M=",
            "type": "github"
        },
        "version": "7f26cf5e27e2bd910ce0ea00c514da2bf97423b8"
    },
    "ltex-extra": {
        "cargoLocks": null,
        "date": "2023-07-28",
        "extract": null,
        "name": "ltex-extra",
        "passthru": null,
        "pinned": false,
        "src": {
            "deepClone": false,
            "fetchSubmodules": false,
            "leaveDotGit": false,
            "name": null,
            "owner": "barreiroleo",
            "repo": "ltex-extra.nvim",
            "rev": "9bed99b2b8488cc2daf66c76d2e0cf051ee80d13",
            "sha256": "sha256-LzgAICiGuaHfYkQq7/4bRJ1M5KopFBcSTVTHrb3rm+w=",
            "type": "github"
        },
        "version": "9bed99b2b8488cc2daf66c76d2e0cf051ee80d13"
    },
    "lualine": {
        "cargoLocks": null,
        "date": "2023-12-26",
        "extract": null,
        "name": "lualine",
        "passthru": null,
        "pinned": false,
        "src": {
            "deepClone": false,
            "fetchSubmodules": false,
            "leaveDotGit": false,
            "name": null,
            "owner": "nvim-lualine",
            "repo": "lualine.nvim",
            "rev": "566b7036f717f3d676362742630518a47f132fff",
            "sha256": "sha256-do28EEtiu14NAroVblx8FJLCk8CVNmpm8RaTbcDHtvk=",
            "type": "github"
        },
        "version": "566b7036f717f3d676362742630518a47f132fff"
    },
    "luasnip": {
        "cargoLocks": null,
        "date": "2024-01-07",
        "extract": null,
        "name": "luasnip",
        "passthru": null,
        "pinned": false,
        "src": {
            "deepClone": false,
            "fetchSubmodules": false,
            "leaveDotGit": false,
            "name": null,
            "owner": "L3MON4D3",
            "repo": "LuaSnip",
            "rev": "2f0db89fcb22d27b908b3609d2441c02798106ab",
            "sha256": "sha256-Kw97CSzj/xnkqi6D/rO7B+BawIcF5A2AECj5cwbhLJc=",
            "type": "github"
        },
        "version": "2f0db89fcb22d27b908b3609d2441c02798106ab"
    },
    "neoconf": {
        "cargoLocks": null,
        "date": "2023-11-04",
        "extract": null,
        "name": "neoconf",
        "passthru": null,
        "pinned": false,
        "src": {
            "deepClone": false,
            "fetchSubmodules": false,
            "leaveDotGit": false,
            "name": null,
            "owner": "folke",
            "repo": "neoconf.nvim",
            "rev": "64437787dba70fce50dad7bfbb97d184c5bc340f",
            "sha256": "sha256-bFnXKttuinBvvJonPPz+8J3+kYgcy7bZvposEKyVnK8=",
            "type": "github"
        },
        "version": "64437787dba70fce50dad7bfbb97d184c5bc340f"
    },
    "neodev": {
        "cargoLocks": null,
        "date": "2024-01-05",
        "extract": null,
        "name": "neodev",
        "passthru": null,
        "pinned": false,
        "src": {
            "deepClone": false,
            "fetchSubmodules": false,
            "leaveDotGit": false,
            "name": null,
            "owner": "folke",
            "repo": "neodev.nvim",
            "rev": "be8d4d4cab6c13c6a572269c9d6a63774baba9a0",
            "sha256": "sha256-guSJ809CDvzbnPyYG8ELr7LEkuX833m5TK+U0hl0hbc=",
            "type": "github"
        },
        "version": "be8d4d4cab6c13c6a572269c9d6a63774baba9a0"
    },
    "neorepl": {
        "cargoLocks": null,
        "date": "2024-01-03",
        "extract": null,
        "name": "neorepl",
        "passthru": null,
        "pinned": false,
        "src": {
            "deepClone": false,
            "fetchSubmodules": false,
            "leaveDotGit": false,
            "name": null,
            "owner": "ii14",
            "repo": "neorepl.nvim",
            "rev": "e60b114217248907a3a1d27bab9988a092865ee0",
            "sha256": "sha256-7Q8KndseaENovxKPD9LWyHBbXaiRsqbDqyW8JJLJBoY=",
            "type": "github"
        },
        "version": "e60b114217248907a3a1d27bab9988a092865ee0"
    },
    "neovim-session-manager": {
        "cargoLocks": null,
        "date": "2023-10-09",
        "extract": null,
        "name": "neovim-session-manager",
        "passthru": null,
        "pinned": false,
        "src": {
            "deepClone": false,
            "fetchSubmodules": false,
            "leaveDotGit": false,
            "name": null,
            "owner": "Shatur",
            "repo": "neovim-session-manager",
            "rev": "68dde355a4304d83b40cf073f53915604bdd8e70",
            "sha256": "sha256-WOJQ6RIibOby+Pmzr6kQxcT2NCGrq1roWkh4QKJECks=",
            "type": "github"
        },
        "version": "68dde355a4304d83b40cf073f53915604bdd8e70"
    },
    "null-ls": {
        "cargoLocks": null,
        "date": "2024-01-03",
        "extract": null,
        "name": "null-ls",
        "passthru": null,
        "pinned": false,
        "src": {
            "deepClone": false,
            "fetchSubmodules": false,
            "leaveDotGit": false,
            "name": null,
            "owner": "nvimtools",
            "repo": "none-ls.nvim",
            "rev": "fbdcbf8e152529af846b3a333f039751829b84c2",
            "sha256": "sha256-RywvfEblN0dukmPVCn0r7+hQr9L1VP5fyHHnOcfvda8=",
            "type": "github"
        },
        "version": "fbdcbf8e152529af846b3a333f039751829b84c2"
    },
    "nvim-cmp": {
        "cargoLocks": null,
        "date": "2023-12-14",
        "extract": null,
        "name": "nvim-cmp",
        "passthru": null,
        "pinned": false,
        "src": {
            "deepClone": false,
            "fetchSubmodules": false,
            "leaveDotGit": false,
            "name": null,
            "owner": "hrsh7th",
            "repo": "nvim-cmp",
            "rev": "538e37ba87284942c1d76ed38dd497e54e65b891",
            "sha256": "sha256-BtAYRYn6m788zAq/mNnbAzAxp1TGf9QkRE0hSOp9sdc=",
            "type": "github"
        },
        "version": "538e37ba87284942c1d76ed38dd497e54e65b891"
    },
    "nvim-colorizer-lua": {
        "cargoLocks": null,
        "date": "2023-12-23",
        "extract": null,
        "name": "nvim-colorizer-lua",
        "passthru": null,
        "pinned": false,
        "src": {
            "deepClone": false,
            "fetchSubmodules": false,
            "leaveDotGit": false,
            "name": null,
            "owner": "nvchad",
            "repo": "nvim-colorizer.lua",
            "rev": "85855b38011114929f4058efc97af1059ab3e41d",
            "sha256": "sha256-oKvFN2K+ASlPNwj2rhptR/ErYgo6XKBPhXSZotDdCP0=",
            "type": "github"
        },
        "version": "85855b38011114929f4058efc97af1059ab3e41d"
    },
    "nvim-dap": {
        "cargoLocks": null,
        "date": "2023-12-20",
        "extract": null,
        "name": "nvim-dap",
        "passthru": null,
        "pinned": false,
        "src": {
            "deepClone": false,
            "fetchSubmodules": false,
            "leaveDotGit": false,
            "name": null,
            "owner": "mfussenegger",
            "repo": "nvim-dap",
            "rev": "f0dca670fa059eb89dda8869a6310c804241345c",
            "sha256": "sha256-UM4BIO/5m5wJGo08Ovguya0RB5T7tYPQ4dH/pVDKun0=",
            "type": "github"
        },
        "version": "f0dca670fa059eb89dda8869a6310c804241345c"
    },
    "nvim-dap-ui": {
        "cargoLocks": null,
        "date": "2024-01-04",
        "extract": null,
        "name": "nvim-dap-ui",
        "passthru": null,
        "pinned": false,
        "src": {
            "deepClone": false,
            "fetchSubmodules": false,
            "leaveDotGit": false,
            "name": null,
            "owner": "rcarriga",
            "repo": "nvim-dap-ui",
            "rev": "7e5e16427aaf814dc2d58e1b219def9ef2fa2435",
            "sha256": "sha256-6PoiV6l+RFfwLH5IkaAwejamZGX9Xey3O0bYeC8a9z0=",
            "type": "github"
        },
        "version": "7e5e16427aaf814dc2d58e1b219def9ef2fa2435"
    },
    "nvim-dap-virtual-text": {
        "cargoLocks": null,
        "date": "2023-12-28",
        "extract": null,
        "name": "nvim-dap-virtual-text",
        "passthru": null,
        "pinned": false,
        "src": {
            "deepClone": false,
            "fetchSubmodules": false,
            "leaveDotGit": false,
            "name": null,
            "owner": "theHamsta",
            "repo": "nvim-dap-virtual-text",
            "rev": "d4542ac257d3c7ee4131350db6179ae6340ce40b",
            "sha256": "sha256-IJMdDcrfsNfxd4rvLVCD1L2FL7Tzm6dV8c0mtEo98vU=",
            "type": "github"
        },
        "version": "d4542ac257d3c7ee4131350db6179ae6340ce40b"
    },
    "nvim-lspconfig": {
        "cargoLocks": null,
        "date": "2024-01-06",
        "extract": null,
        "name": "nvim-lspconfig",
        "passthru": null,
        "pinned": false,
        "src": {
            "deepClone": false,
            "fetchSubmodules": false,
            "leaveDotGit": false,
            "name": null,
            "owner": "neovim",
            "repo": "nvim-lspconfig",
            "rev": "796394fd19fb878e8dbc4fd1e9c9c186ed07a5f4",
            "sha256": "sha256-CsMf78TIzvB9OETUOSxj2lFPdZFnIna1keCotq8SvZw=",
            "type": "github"
        },
        "version": "796394fd19fb878e8dbc4fd1e9c9c186ed07a5f4"
    },
    "nvim-navic": {
        "cargoLocks": null,
        "date": "2023-11-30",
        "extract": null,
        "name": "nvim-navic",
        "passthru": null,
        "pinned": false,
        "src": {
            "deepClone": false,
            "fetchSubmodules": false,
            "leaveDotGit": false,
            "name": null,
            "owner": "SmiteshP",
            "repo": "nvim-navic",
            "rev": "8649f694d3e76ee10c19255dece6411c29206a54",
            "sha256": "sha256-0p5n/V8Jlj9XyxV/fuMwsbQ7oV5m9H2GqZZEA/njxCQ=",
            "type": "github"
        },
        "version": "8649f694d3e76ee10c19255dece6411c29206a54"
    },
    "nvim-notify": {
        "cargoLocks": null,
        "date": "2024-01-03",
        "extract": null,
        "name": "nvim-notify",
        "passthru": null,
        "pinned": false,
        "src": {
            "deepClone": false,
            "fetchSubmodules": false,
            "leaveDotGit": false,
            "name": null,
            "owner": "rcarriga",
            "repo": "nvim-notify",
            "rev": "1576123bff3bed67bc673a3076e591abfe5d8ca9",
            "sha256": "sha256-2+FuMzc8AymAAXo0yxVSNVn09iFbqbEMGW4UeFuFVrM=",
            "type": "github"
        },
        "version": "1576123bff3bed67bc673a3076e591abfe5d8ca9"
    },
    "nvim-spectre": {
        "cargoLocks": null,
        "date": "2023-12-20",
        "extract": null,
        "name": "nvim-spectre",
        "passthru": null,
        "pinned": false,
        "src": {
            "deepClone": false,
            "fetchSubmodules": false,
            "leaveDotGit": false,
            "name": null,
            "owner": "nvim-pack",
            "repo": "nvim-spectre",
            "rev": "d8906855f1949ac97b1e77aaf8d3fe12ed158ddc",
            "sha256": "sha256-hK1DiVWsHyuAp7+xvIAy8Sag+nXC6U0yacKUSF8wvM4=",
            "type": "github"
        },
        "version": "d8906855f1949ac97b1e77aaf8d3fe12ed158ddc"
    },
    "nvim-surround": {
        "cargoLocks": null,
        "date": "2023-12-04",
        "extract": null,
        "name": "nvim-surround",
        "passthru": null,
        "pinned": false,
        "src": {
            "deepClone": false,
            "fetchSubmodules": false,
            "leaveDotGit": false,
            "name": null,
            "owner": "kylechui",
            "repo": "nvim-surround",
            "rev": "633a0ab03159569a66b65671b0ffb1a6aed6cf18",
            "sha256": "sha256-ph4obOW+l+TGZp6B4R4ZZtjiFMKWKFKigV3aLLPhbGs=",
            "type": "github"
        },
        "version": "633a0ab03159569a66b65671b0ffb1a6aed6cf18"
    },
    "nvim-tree-lua": {
        "cargoLocks": null,
        "date": "2024-01-07",
        "extract": null,
        "name": "nvim-tree-lua",
        "passthru": null,
        "pinned": false,
        "src": {
            "deepClone": false,
            "fetchSubmodules": false,
            "leaveDotGit": false,
            "name": null,
            "owner": "nvim-tree",
            "repo": "nvim-tree.lua",
            "rev": "78a5836092617205a999aefc75be1d842c299cbc",
            "sha256": "sha256-/Zz15BBm9sqOLK39wiHg5dQb38C18J8CSFR3B8qsHdA=",
            "type": "github"
        },
        "version": "78a5836092617205a999aefc75be1d842c299cbc"
    },
    "nvim-treesitter": {
        "cargoLocks": null,
        "date": "2024-01-07",
        "extract": null,
        "name": "nvim-treesitter",
        "passthru": null,
        "pinned": false,
        "src": {
            "deepClone": false,
            "fetchSubmodules": false,
            "leaveDotGit": false,
            "name": null,
            "owner": "nvim-treesitter",
            "repo": "nvim-treesitter",
            "rev": "8cd2b230174efbf7b5d9f49fe2f90bda6b5eb16e",
            "sha256": "sha256-Xc5XqHy3Yk82BFZjeLRSoaN4U4v46FAclFcjoRHZ9no=",
            "type": "github"
        },
        "version": "8cd2b230174efbf7b5d9f49fe2f90bda6b5eb16e"
    },
    "nvim-treesitter-context": {
        "cargoLocks": null,
        "date": "2023-12-23",
        "extract": null,
        "name": "nvim-treesitter-context",
        "passthru": null,
        "pinned": false,
        "src": {
            "deepClone": false,
            "fetchSubmodules": false,
            "leaveDotGit": false,
            "name": null,
            "owner": "nvim-treesitter",
            "repo": "nvim-treesitter-context",
            "rev": "652ec514d6ba8bc4a3c2de76c855fe668e2c7196",
            "sha256": "sha256-g+E64X72s5GQANtj7LrvlcV3HLJQ0tCZQvfXCqFhyfg=",
            "type": "github"
        },
        "version": "652ec514d6ba8bc4a3c2de76c855fe668e2c7196"
    },
    "nvim-treesitter-textobjects": {
        "cargoLocks": null,
        "date": "2024-01-01",
        "extract": null,
        "name": "nvim-treesitter-textobjects",
        "passthru": null,
        "pinned": false,
        "src": {
            "deepClone": false,
            "fetchSubmodules": false,
            "leaveDotGit": false,
            "name": null,
            "owner": "nvim-treesitter",
            "repo": "nvim-treesitter-textobjects",
            "rev": "85b9d0cbd4ff901abcda862b50dbb34e0901848b",
            "sha256": "sha256-2Kdiuos0x43Hx2hxjxpGpC1uP9c/rI0eW20XJMkz5E8=",
            "type": "github"
        },
        "version": "85b9d0cbd4ff901abcda862b50dbb34e0901848b"
    },
    "nvim-web-devicons": {
        "cargoLocks": null,
        "date": "2024-01-06",
        "extract": null,
        "name": "nvim-web-devicons",
        "passthru": null,
        "pinned": false,
        "src": {
            "deepClone": false,
            "fetchSubmodules": false,
            "leaveDotGit": false,
            "name": null,
            "owner": "nvim-tree",
            "repo": "nvim-web-devicons",
            "rev": "db0c864375c198cacc171ff373e76bfce2a85045",
            "sha256": "sha256-xVLj36te9JFoK461RQ/Lwt/UublQVsD4SG0BEIcmkeI=",
            "type": "github"
        },
        "version": "db0c864375c198cacc171ff373e76bfce2a85045"
    },
    "obsidian-nvim": {
        "cargoLocks": null,
        "date": "2024-01-06",
        "extract": null,
        "name": "obsidian-nvim",
        "passthru": null,
        "pinned": false,
        "src": {
            "deepClone": false,
            "fetchSubmodules": false,
            "leaveDotGit": false,
            "name": null,
            "owner": "epwalsh",
            "repo": "obsidian.nvim",
            "rev": "2d02fe914883f7de6ff4481f46b0081ccda5150b",
            "sha256": "sha256-Nlp+mi3x1MXHwDGt0cOdeLhGUxcEcHkB3AZyGRadRyo=",
            "type": "github"
        },
        "version": "2d02fe914883f7de6ff4481f46b0081ccda5150b"
    },
    "plenary": {
        "cargoLocks": null,
        "date": "2023-11-30",
        "extract": null,
        "name": "plenary",
        "passthru": null,
        "pinned": false,
        "src": {
            "deepClone": false,
            "fetchSubmodules": false,
            "leaveDotGit": false,
            "name": null,
            "owner": "nvim-lua",
            "repo": "plenary.nvim",
            "rev": "55d9fe89e33efd26f532ef20223e5f9430c8b0c0",
            "sha256": "sha256-f8YVaXMG0ZyW6iotAgnftaYULnL69UPolRad6RTG27g=",
            "type": "github"
        },
        "version": "55d9fe89e33efd26f532ef20223e5f9430c8b0c0"
    },
    "py_lsp": {
        "cargoLocks": null,
        "date": "2023-02-28",
        "extract": null,
        "name": "py_lsp",
        "passthru": null,
        "pinned": false,
        "src": {
            "deepClone": false,
            "fetchSubmodules": false,
            "leaveDotGit": false,
            "name": null,
            "owner": "hallerpatrick",
            "repo": "py_lsp.nvim",
            "rev": "5b2bd6433a2dbab76d54d58ccc1d1e89b220091c",
            "sha256": "sha256-YOYrumIYlWcZBL1LSeBWseb/0G4n8obcll6wPwaXqpM=",
            "type": "github"
        },
        "version": "5b2bd6433a2dbab76d54d58ccc1d1e89b220091c"
    },
    "rainbow-delimiters": {
        "cargoLocks": null,
        "date": "2024-01-07",
        "extract": null,
        "name": "rainbow-delimiters",
        "passthru": null,
        "pinned": false,
        "src": {
            "deepClone": false,
            "fetchSubmodules": false,
            "leaveDotGit": false,
            "name": null,
            "owner": "hiphish",
            "repo": "rainbow-delimiters.nvim",
            "rev": "18d1350ec3897e7282b4cbf78ef6f50191ae78f8",
            "sha256": "sha256-7aj7EsFOLfpxryZd0hQTLZHaw7uZ/XkgbHqleTUZxXQ=",
            "type": "github"
        },
        "version": "18d1350ec3897e7282b4cbf78ef6f50191ae78f8"
    },
    "rust-tools": {
        "cargoLocks": null,
        "date": "2024-01-03",
        "extract": null,
        "name": "rust-tools",
        "passthru": null,
        "pinned": false,
        "src": {
            "deepClone": false,
            "fetchSubmodules": false,
            "leaveDotGit": false,
            "name": null,
            "owner": "simrat39",
            "repo": "rust-tools.nvim",
            "rev": "676187908a1ce35ffcd727c654ed68d851299d3e",
            "sha256": "sha256-kFane5ze7VDiOzF7jdmXkr50XQsNvdb+a9HQtybEVE0=",
            "type": "github"
        },
        "version": "676187908a1ce35ffcd727c654ed68d851299d3e"
    },
    "schemastore": {
        "cargoLocks": null,
        "date": "2024-01-07",
        "extract": null,
        "name": "schemastore",
        "passthru": null,
        "pinned": false,
        "src": {
            "deepClone": false,
            "fetchSubmodules": false,
            "leaveDotGit": false,
            "name": null,
            "owner": "b0o",
            "repo": "schemastore.nvim",
            "rev": "d71620c082b269fe5b56be465b52465b5424015f",
            "sha256": "sha256-zsJvwvAfNCZuY/Fku4Jms0pM67M6ssCWla2TpqG8nso=",
            "type": "github"
        },
        "version": "d71620c082b269fe5b56be465b52465b5424015f"
    },
    "telescope": {
        "cargoLocks": null,
        "date": "2024-01-04",
        "extract": null,
        "name": "telescope",
        "passthru": null,
        "pinned": false,
        "src": {
            "deepClone": false,
            "fetchSubmodules": false,
            "leaveDotGit": false,
            "name": null,
            "owner": "nvim-telescope",
            "repo": "telescope.nvim",
            "rev": "87e92ea31b2b61d45ad044cf7b2d9b66dad2a618",
            "sha256": "sha256-ImHPPyodo/8RHOR0EyhRqIpmNo1C7i41yakEQlE9fj4=",
            "type": "github"
        },
        "version": "87e92ea31b2b61d45ad044cf7b2d9b66dad2a618"
    },
    "telescope-file-browser": {
        "cargoLocks": null,
        "date": "2023-12-26",
        "extract": null,
        "name": "telescope-file-browser",
        "passthru": null,
        "pinned": false,
        "src": {
            "deepClone": false,
            "fetchSubmodules": false,
            "leaveDotGit": false,
            "name": null,
            "owner": "nvim-telescope",
            "repo": "telescope-file-browser.nvim",
            "rev": "4bd5657b14b58e069287f5ac591a647bb860b2ed",
            "sha256": "sha256-lqgRNIJGCFYEnGbxqlAXZG1lO09KJOM+J9oFuEVMHkg=",
            "type": "github"
        },
        "version": "4bd5657b14b58e069287f5ac591a647bb860b2ed"
    },
    "telescope-project": {
        "cargoLocks": null,
        "date": "2023-12-01",
        "extract": null,
        "name": "telescope-project",
        "passthru": null,
        "pinned": false,
        "src": {
            "deepClone": false,
            "fetchSubmodules": false,
            "leaveDotGit": false,
            "name": null,
            "owner": "nvim-telescope",
            "repo": "telescope-project.nvim",
            "rev": "1aaf16580a614601a7f7077d9639aeb457dc5559",
            "sha256": "sha256-touMCltcnqkrQYV1NtNeWLQeFVGt+WM3aIWIdKilA7w=",
            "type": "github"
        },
        "version": "1aaf16580a614601a7f7077d9639aeb457dc5559"
    },
    "telescope-ui-select": {
        "cargoLocks": null,
        "date": "2023-12-04",
        "extract": null,
        "name": "telescope-ui-select",
        "passthru": null,
        "pinned": false,
        "src": {
            "deepClone": false,
            "fetchSubmodules": false,
            "leaveDotGit": false,
            "name": null,
            "owner": "nvim-telescope",
            "repo": "telescope-ui-select.nvim",
            "rev": "6e51d7da30bd139a6950adf2a47fda6df9fa06d2",
            "sha256": "sha256-YRhNmmG4gx9Ht8JwjQfbTjJyTHEuZmtP6lqnhOsk8bE=",
            "type": "github"
        },
        "version": "6e51d7da30bd139a6950adf2a47fda6df9fa06d2"
    },
    "todo-comments": {
        "cargoLocks": null,
        "date": "2023-10-25",
        "extract": null,
        "name": "todo-comments",
        "passthru": null,
        "pinned": false,
        "src": {
            "deepClone": false,
            "fetchSubmodules": false,
            "leaveDotGit": false,
            "name": null,
            "owner": "folke",
            "repo": "todo-comments.nvim",
            "rev": "4a6737a8d70fe1ac55c64dfa47fcb189ca431872",
            "sha256": "sha256-Z041A05I2zESNV+aSghtnijEUeDqPjLQxiOcCVVOwfE=",
            "type": "github"
        },
        "version": "4a6737a8d70fe1ac55c64dfa47fcb189ca431872"
    },
    "toggleterm": {
        "cargoLocks": null,
        "date": "2023-12-25",
        "extract": null,
        "name": "toggleterm",
        "passthru": null,
        "pinned": false,
        "src": {
            "deepClone": false,
            "fetchSubmodules": false,
            "leaveDotGit": false,
            "name": null,
            "owner": "akinsho",
            "repo": "toggleterm.nvim",
            "rev": "e3805fed94d487b81e9c21548535cc820f62f840",
            "sha256": "sha256-eraEi70xR8+lGYzPcf6tJUSDJXr1hsSYmIYKj1LZ9U8=",
            "type": "github"
        },
        "version": "e3805fed94d487b81e9c21548535cc820f62f840"
    },
    "trouble": {
        "cargoLocks": null,
        "date": "2023-10-18",
        "extract": null,
        "name": "trouble",
        "passthru": null,
        "pinned": false,
        "src": {
            "deepClone": false,
            "fetchSubmodules": false,
            "leaveDotGit": false,
            "name": null,
            "owner": "folke",
            "repo": "trouble.nvim",
            "rev": "f1168feada93c0154ede4d1fe9183bf69bac54ea",
            "sha256": "sha256-8nLghiueYOtWY7OGVxow9A2G/5lgt+Kt5D8q1xeJvVg=",
            "type": "github"
        },
        "version": "f1168feada93c0154ede4d1fe9183bf69bac54ea"
    },
    "typescript-tools": {
        "cargoLocks": null,
        "date": "2023-12-19",
        "extract": null,
        "name": "typescript-tools",
        "passthru": null,
        "pinned": false,
        "src": {
            "deepClone": false,
            "fetchSubmodules": false,
            "leaveDotGit": false,
            "name": null,
            "owner": "pmizio",
            "repo": "typescript-tools.nvim",
            "rev": "829b5dc4f6704b249624e5157ad094dcb20cdc6b",
            "sha256": "sha256-O/wJzIflMXUc8FbeiUcYuWgE4md8gjK7KUifWFYZNXg=",
            "type": "github"
        },
        "version": "829b5dc4f6704b249624e5157ad094dcb20cdc6b"
    },
    "vim-fugitive": {
        "cargoLocks": null,
        "date": "2023-12-15",
        "extract": null,
        "name": "vim-fugitive",
        "passthru": null,
        "pinned": false,
        "src": {
            "deepClone": false,
            "fetchSubmodules": false,
            "leaveDotGit": false,
            "name": null,
            "owner": "tpope",
            "repo": "vim-fugitive",
            "rev": "59659093581aad2afacedc81f009ed6a4bfad275",
            "sha256": "sha256-OxjbAaKiExx0081ALFf4FtPH2L6xbDsSDGTifYowtMA=",
            "type": "github"
        },
        "version": "59659093581aad2afacedc81f009ed6a4bfad275"
    },
    "vim-table-mode": {
        "cargoLocks": null,
        "date": "2023-10-29",
        "extract": null,
        "name": "vim-table-mode",
        "passthru": null,
        "pinned": false,
        "src": {
            "deepClone": false,
            "fetchSubmodules": false,
            "leaveDotGit": false,
            "name": null,
            "owner": "dhruvasagar",
            "repo": "vim-table-mode",
            "rev": "4ff8de2ac93431ee6d85a9e04177012752e6abdc",
            "sha256": "sha256-8o6PMbnlRf0kQHJxSygxq+zv3Xyh7TURiKopyE6A7XI=",
            "type": "github"
        },
        "version": "4ff8de2ac93431ee6d85a9e04177012752e6abdc"
    },
    "which-key": {
        "cargoLocks": null,
        "date": "2023-10-20",
        "extract": null,
        "name": "which-key",
        "passthru": null,
        "pinned": false,
        "src": {
            "deepClone": false,
            "fetchSubmodules": false,
            "leaveDotGit": false,
            "name": null,
            "owner": "folke",
            "repo": "which-key.nvim",
            "rev": "4433e5ec9a507e5097571ed55c02ea9658fb268a",
            "sha256": "sha256-uvghPj/teWrRMm09Gh8iQ/LV2nYJw0lmoiZK6L4+1cY=",
            "type": "github"
        },
        "version": "4433e5ec9a507e5097571ed55c02ea9658fb268a"
    }
}